cforces/__init__.py
cforces/client.py
cforces/utils.py
cforces/enums/__init__.py
cforces/enums/contest_phase.py
cforces/enums/contest_type.py
cforces/enums/participant_type.py
cforces/enums/problem_result_type.py
cforces/enums/problem_type.py
cforces/enums/rank.py
cforces/enums/testset.py
cforces/enums/verdict.py
cforces/errors/__init__.py
cforces/errors/api.py
cforces/errors/base.py
cforces/methods/__init__.py
cforces/methods/blog_entry.py
cforces/methods/contest.py
cforces/methods/problemset.py
cforces/methods/recent_actions.py
cforces/methods/user.py
cforces/types/__init__.py
cforces/types/object.py
cforces/types/blog/__init__.py
cforces/types/blog/blog_entry.py
cforces/types/blog/comment.py
cforces/types/blog/recent_action.py
cforces/types/contest/__init__.py
cforces/types/contest/contest.py
cforces/types/contest/ranklist_row.py
cforces/types/contest/rating_change.py
cforces/types/contest/standings.py
cforces/types/problem/__init__.py
cforces/types/problem/hack.py
cforces/types/problem/problem.py
cforces/types/problem/problem_result.py
cforces/types/problem/problem_statistics.py
cforces/types/problem/submission.py
cforces/types/user/__init__.py
cforces/types/user/member.py
cforces/types/user/party.py
cforces/types/user/user.py
cforces-0.2.0.dist-info/LICENSE
cforces-0.2.0.dist-info/METADATA
cforces-0.2.0.dist-info/WHEEL
cforces-0.2.0.dist-info/top_level.txt
cforces-0.2.0.dist-info/RECORD
