Metadata-Version: 2.1
Name: cforces
Version: 0.2.0
Summary: A Codeforces API wrapper
Author-email: Boris Martinez <x93bd0@gmail.com>
Project-URL: Homepage, https://github.com/x93bd0/cforces
Project-URL: Issues, https://github.com/x93bd0/cforces/issues
Classifier: Programming Language :: Python :: 3
Classifier: License :: OSI Approved :: MIT License
Classifier: Operating System :: OS Independent
Requires-Python: >=3.8
License-File: LICENSE
Requires-Dist: aiohttp
